leocense/__init__.py
leocense/client.py
leocense/device.py
leocense-1.1.1.dist-info/METADATA
leocense-1.1.1.dist-info/WHEEL
leocense-1.1.1.dist-info/top_level.txt
leocense-1.1.1.dist-info/RECORD
